{
  "last_updated": "2026-03-07T20:28:05.947689+00:00",
  "confirmed_count": 1,
  "newly_added": 0,
  "confirmed_projects": [
    {
      "id": "dc97dbdd966082",
      "company": "Amazon (AWS)",
      "project": "Amazon to invest $21B more in Spain with focus on data centers",
      "location": "Spain",
      "capex_b": 21.05,
      "status": "Auto-Confirmed",
      "scale": "$21.1B | Detected: 2026-03-03",
      "notes": "Auto-confirmed by project intelligence scanner. Companies detected: Amazon. Amounts detected: $21B, $21.05 billion. Original headline: \"Amazon to invest $21B more in Spain with focus on data centers\"",
      "source": "SiliconAngle",
      "url": "https://siliconangle.com/2026/03/02/amazon-invest-another-21b-spain-focus-data-centers/",
      "year": 2026,
      "detected_date": "2026-03-03",
      "confidence": 9,
      "auto_detected": true,
      "finding_type": "New Project"
    }
  ]
}